rtl/top.sv
module top #(parameter int HALF_PERIOD_CYCLES = 12500000) (
    input logic clk_25mhz,
    output logic led
);
    initial led = 0;
    int clk_count = 0;

    always_ff @(posedge clk_25mhz) begin
        if (clk_count == HALF_PERIOD_CYCLES - 1) begin
            clk_count <= 0;
            led <= ~led;
        end
        else clk_count <= clk_count + 1;
    end
endmodule

sim/tb_top.sv
`timescale 1ns/1ps

module tb_top;

parameter int HALF_PERIOD_CYCLES = 7;

int passed_cycles = 0;
localparam cycles_to_pass = 10;

logic clk = 0;
logic led;

initial begin
    $dumpfile("build/blink.vcd");
    $dumpvars(0, tb_top);
end

initial begin
    #3000;
    $fatal(1, "Timeout error.");
end

always #20 clk = ~clk;

top #(.HALF_PERIOD_CYCLES(HALF_PERIOD_CYCLES)) dut (
    .clk_25mhz(clk),
    .led(led)
  );

initial begin
    //Check if the led if originally off
    #1ps;
    if (led !== 1'b0) 
        $fatal(1, "Led does not start low.");
end

localparam time first_toggle = 20 + (HALF_PERIOD_CYCLES - 1) * 40;
localparam time toggle_period = HALF_PERIOD_CYCLES * 40;

time change_allowed = first_toggle;

logic first_led_fire = 1;
always @(led) begin
    //Check if led glitches between cycles.
    if (first_led_fire)
        first_led_fire = 0;
    else if ($time !== change_allowed)
        $fatal(1, "Led changed at unexpected time %t", $time);
    change_allowed += toggle_period;
end

int clk_cycles = 0;

always @(posedge clk) begin
    //Ensure that led is never X/Z
    #1ps;
    if (led === 1'bx || led === 1'bz)
        $fatal(1, "Led is X/Z."); 

    //Check that led follows cycles properly.
    if (clk_cycles < HALF_PERIOD_CYCLES - 1) begin
        if (led !== 1'b0) 
            $fatal(1, "Led is not low when expected");
        clk_cycles <= clk_cycles + 1;
        passed_cycles <= passed_cycles + 1;
    end
    else begin
        if (led !== 1'b1) 
            $fatal(1, "Led is not high when expected");
        clk_cycles <= 0;
        passed_cycles <= passed_cycles + 1;
    end
end

always @(passed_cycles) begin
    if (passed_cycles === cycles_to_pass) begin
        $display("PASS");
        $finish;
    end
end

endmodule

build/blink.vcd
$date
	Mon Sep 28 23:53:40 2026
$end
$version
	Icarus Verilog
$end
$timescale
	1ps
$end
$scope module tb_top $end
$var wire 1 ! led $end
$var parameter 32 " HALF_PERIOD_CYCLES $end
$var parameter 32 # cycles_to_pass $end
$var parameter 64 $ first_toggle $end
$var parameter 64 % toggle_period $end
$var reg 64 & change_allowed [63:0] $end
$var reg 1 ' clk $end
$var reg 1 ( first_led_fire $end
$var integer 32 ) clk_cycles [31:0] $end
$var integer 32 * passed_cycles [31:0] $end
$scope module dut $end
$var wire 1 ' clk_25mhz $end
$var parameter 32 + HALF_PERIOD_CYCLES $end
$var reg 1 ! led $end
$var integer 32 , clk_count [31:0] $end
$upscope $end
$upscope $end
$enddefinitions $end
$comment Show the parameter values. $end
$dumpall
b110 +
b11110000 %
b11011100 $
b1010 #
b110 "
$end
#0
$dumpvars
b0 ,
b0 *
b0 )
0(
0'
b111001100 &
0!
$end
#20000
b1 ,
1'
#20001
b1 *
b1 )
#40000
0'
#60000
b10 ,
1'
#60001
b10 *
b10 )
#80000
0'
#100000
b11 ,
1'
#100001
b11 *
b11 )
#120000
0'
#140000
b100 ,
1'
#140001
b100 *
b100 )
#160000
0'
#180000
b101 ,
1'
#180001
b101 *
b101 )
#200000
0'
#220000
1!
b0 ,
1'
