rtl/top.sv
module top #(parameter int HALF_PERIOD_CYCLES = 12500000) (
    input logic clk_25mhz,
    output logic led
);
    initial led = 0;
    int clk_count = 0;

    always_ff @(posedge clk_25mhz) begin
        if (clk_count == HALF_PERIOD_CYCLES - 1) begin
            clk_count <= 0;
            led <= ~led;
        end
        else clk_count <= clk_count + 1;
    end
endmodule

sim/tb_top.sv
`timescale 1ns/1ps

module tb_top;

parameter int HALF_PERIOD_CYCLES = 7;

int passed_cycles = 0;
localparam cycles_to_pass = 30;

logic clk = 0;
logic led;

initial begin
    $dumpfile("build/blink.vcd");
    $dumpvars(0, tb_top);
end

initial begin
    #3000;
    $fatal(1, "Timeout error.");
end

always #20 clk = ~clk;

top #(.HALF_PERIOD_CYCLES(HALF_PERIOD_CYCLES)) dut (
    .clk_25mhz(clk),
    .led(led)
  );

initial begin
    //Check if the led if originally off
    #1ps;
    if (led !== 1'b0) 
        $fatal(1, "Led does not start low.");
end

localparam time first_toggle = 20 + (HALF_PERIOD_CYCLES - 1) * 40;
localparam time toggle_period = HALF_PERIOD_CYCLES * 40;

time change_allowed = first_toggle;

always @(led) begin
    if ($time != 0) begin
        if ($time !== change_allowed)
            $fatal(1, "Led changed at unexpected time %t", $time);
        change_allowed += toggle_period;
    end
end

int edge_count = 0;
logic expected_led;

always @(posedge clk) begin
    #1ps;
    edge_count++;

    if (led === 1'bx || led === 1'bz)
        $fatal(1, "Led is X/Z."); 

    expected_led = (((edge_count / HALF_PERIOD_CYCLES) % 2) == 1);
    if (led !== expected_led)
        $fatal(1, "Led is %b at edge %0d, expected %b", led, edge_count, expected_led);

    passed_cycles <= passed_cycles + 1;
end

always @(passed_cycles) begin
    if (passed_cycles === cycles_to_pass) begin
        $display("PASS");
        $finish;
    end
end

endmodule

build/blink.vcd
$date
	Tue Sep 29 00:40:18 2026
$end
$version
	Icarus Verilog
$end
$timescale
	1ps
$end
$scope module tb_top $end
$var wire 1 ! led $end
$var parameter 32 " HALF_PERIOD_CYCLES $end
$var parameter 32 # cycles_to_pass $end
$var parameter 64 $ first_toggle $end
$var parameter 64 % toggle_period $end
$var reg 64 & change_allowed [63:0] $end
$var reg 1 ' clk $end
$var reg 1 ( expected_led $end
$var integer 32 ) edge_count [31:0] $end
$var integer 32 * passed_cycles [31:0] $end
$scope module dut $end
$var wire 1 ' clk_25mhz $end
$var parameter 32 + HALF_PERIOD_CYCLES $end
$var reg 1 ! led $end
$var integer 32 , clk_count [31:0] $end
$upscope $end
$upscope $end
$enddefinitions $end
$comment Show the parameter values. $end
$dumpall
b110 +
b11110000 %
b11011100 $
b11110 #
b110 "
$end
#0
$dumpvars
b0 ,
b0 *
b0 )
x(
0'
b11011100 &
0!
$end
#20000
b1 ,
1'
#20001
b1 *
0(
b1 )
#40000
0'
#60000
b10 ,
1'
#60001
b10 *
b10 )
#80000
0'
#100000
b11 ,
1'
#100001
b11 *
b11 )
#120000
0'
#140000
b100 ,
1'
#140001
b100 *
b100 )
#160000
0'
#180000
b101 ,
1'
#180001
b101 *
b101 )
#200000
0'
#220000
b111001100 &
1!
b0 ,
1'
#220001
b110 *
1(
b110 )
#240000
0'
#260000
b1 ,
1'
#260001
b111 *
b111 )
#280000
0'
#300000
b10 ,
1'
#300001
b1000 *
b1000 )
#320000
0'
#340000
b11 ,
1'
#340001
b1001 *
b1001 )
#360000
0'
#380000
b100 ,
1'
#380001
b1010 *
b1010 )
#400000
0'
#420000
b101 ,
1'
#420001
b1011 *
b1011 )
#440000
0'
#460000
b1010111100 &
0!
b0 ,
1'
#460001
b1100 *
0(
b1100 )
#480000
0'
#500000
b1 ,
1'
#500001
b1101 *
b1101 )
#520000
0'
#540000
b10 ,
1'
#540001
b1110 *
b1110 )
#560000
0'
#580000
b11 ,
1'
#580001
b1111 *
b1111 )
#600000
0'
#620000
b100 ,
1'
#620001
b10000 *
b10000 )
#640000
0'
#660000
b101 ,
1'
#660001
b10001 *
b10001 )
#680000
0'
#700000
b1110101100 &
1!
b0 ,
1'
#700001
b10010 *
1(
b10010 )
#720000
0'
#740000
b1 ,
1'
#740001
b10011 *
b10011 )
#760000
0'
#780000
b10 ,
1'
#780001
b10100 *
b10100 )
#800000
0'
#820000
b11 ,
1'
#820001
b10101 *
b10101 )
#840000
0'
#860000
b100 ,
1'
#860001
b10110 *
b10110 )
#880000
0'
#900000
b101 ,
1'
#900001
b10111 *
b10111 )
#920000
0'
#940000
b10010011100 &
0!
b0 ,
1'
#940001
b11000 *
0(
b11000 )
#960000
0'
#980000
b1 ,
1'
#980001
b11001 *
b11001 )
#1000000
0'
#1020000
b10 ,
1'
#1020001
b11010 *
b11010 )
#1040000
0'
#1060000
b11 ,
1'
#1060001
b11011 *
b11011 )
#1080000
0'
#1100000
b100 ,
1'
#1100001
b11100 *
b11100 )
#1120000
0'
#1140000
b101 ,
1'
#1140001
b11101 *
b11101 )
#1160000
0'
#1180000
b10110001100 &
1!
b0 ,
1'
#1180001
b11110 *
1(
b11110 )
